etypography/__init__.py
etypography/_break_text.py
etypography/_font.py
etypography/_font_face.py
etypography/_unicode.py
etypography/py.typed
etypography-0.10.0.dist-info/METADATA
etypography-0.10.0.dist-info/WHEEL
etypography-0.10.0.dist-info/RECORD
