Metadata-Version: 2.1
Name: etypography
Version: 0.10.0
Summary: Layout text.
Author: Erik Soma
Author-email: stillusingirc@gmail.com
Requires-Python: >=3.12,<4.0
Classifier: Programming Language :: Python :: 3
Classifier: Programming Language :: Python :: 3.12
Classifier: Programming Language :: Python :: 3.13
Requires-Dist: egeometry (>=0,<1)
Requires-Dist: emath (>=0,<1)
Requires-Dist: freetype-py (>=2.5.1,<3.0.0)
Requires-Dist: uharfbuzz (>=0.45.0,<0.46.0)
